Workbook

Sheet P&L
A1: Insert Year | B1: January | C1: February | D1: March | E1: April | F1: May | G1: June | H1: July | I1: August | J1: September | K1: October | L1: November | M1: December
A2: Dues - Monthly Membership
A3: Enhancement Fees
A4: Healthy Contributions Income
A5: Personal Training
A6: Refunds
A7: Reimbursements
A8: Ancillary Sales1
A9: Other Misc Sales
A10: Vending
A11: Total Revenue | B11: =SUM(B2:B10) -> 0 | C11: =SUM(C2:C10) -> 0 | D11: =SUM(D2:D10) -> 0 | E11: =SUM(E2:E10) -> 0 | F11: =SUM(F2:F10) -> 0 | G11: =SUM(G2:G10) -> 0 | H11: =SUM(H2:H10) -> 0 | I11: =SUM(I2:I10) -> 0 | ... M11: =SUM(M2:M10) -> 0
A13: Consumables Cost2
A14: Merchant Service Fees
A15: Healthy Contributions Fees
A16: Administrative Fees3
A17: Credit Card Pass Through Fees
A18: Contract Storage Fee
A19: Processing Fees4
A20: Key Fobs Expense
A21: Freight & Shipping
A22: Training Dept Salary/Wages
A23: Training Dept Bonus
A24: Training Dept Commissions
A25: Total Cost of Goods/Services | B25: =SUM(B13:B24) -> 0 | C25: =SUM(C13:C24) -> 0 | D25: =SUM(D13:D24) -> 0 | E25: =SUM(E13:E24) -> 0 | F25: =SUM(F13:F24) -> 0 | G25: =SUM(G13:G24) -> 0 | H25: =SUM(H13:H24) -> 0 | I25: =SUM(I13:I24) -> 0 | ... M25: =SUM(M13:M24) -> 0
A27: Gross Profit | B27: =B11-B25 -> 0 | C27: =C11-C25 -> 0 | D27: =D11-D25 -> 0 | E27: =E11-E25 -> 0 | F27: =F11-F25 -> 0 | G27: =G11-G25 -> 0 | H27: =H11-H25 -> 0 | I27: =I11-I25 -> 0 | ... M27: =M11-M25 -> 0
A28: Gross Proft % | B28: =B27/B11 -> #DIV/0! | C28: =C27/C11 -> #DIV/0! | D28: =D27/D11 -> #DIV/0! | E28: =E27/E11 -> #DIV/0! | F28: =F27/F11 -> #DIV/0! | G28: =G27/G11 -> #DIV/0! | H28: =H27/H11 -> #DIV/0! | I28: =I27/I11 -> #DIV/0! | ... M28: =M27/M11 -> #DIV/0!
A30: Management Salary
A31: Other Salaries/Wages
A32: Commissions
A33: Bonuses
A34: Total Personnel | B34: =SUM(B30:B33) -> 0 | C34: =SUM(C30:C33) -> 0 | D34: =SUM(D30:D33) -> 0 | E34: =SUM(E30:E33) -> 0 | F34: =SUM(F30:F33) -> 0 | G34: =SUM(G30:G33) -> 0 | H34: =SUM(H30:H33) -> 0 | I34: =SUM(I30:I33) -> 0 | ... M34: =SUM(M30:M33) -> 0
A36: Training/Development5
A37: Employer Taxes
A38: Employee Recruiting6
A39: Total Personnel (Other Costs) | B39: =SUM(B36:B38) -> 0 | C39: =SUM(C36:C38) -> 0 | D39: =SUM(D36:D38) -> 0 | E39: =SUM(E36:E38) -> 0 | F39: =SUM(F36:F38) -> 0 | G39: =SUM(G36:G38) -> 0 | H39: =SUM(H36:H38) -> 0 | I39: =SUM(I36:I38) -> 0 | ... M39: =SUM(M36:M38) -> 0
A41: Rent Expense
A42: Electric
A43: Cleaning/Janitorial
A44: Repairs and Maintenance
A45: Water
A46: Total Facility | B46: =SUM(B41:B45) -> 0 | C46: =SUM(C41:C45) -> 0 | D46: =SUM(D41:D45) -> 0 | E46: =SUM(E41:E45) -> 0 | F46: =SUM(F41:F45) -> 0 | G46: =SUM(G41:G45) -> 0 | H46: =SUM(H41:H45) -> 0 | I46: =SUM(I41:I45) -> 0 | ... M46: =SUM(M41:M45) -> 0
A48: General Liability Insurance
A49: Total Insurance | B49: =B48 -> 0 | C49: =C48 -> 0 | D49: =D48 -> 0 | E49: =E48 -> 0 | F49: =F48 -> 0 | G49: =G48 -> 0 | H49: =H48 -> 0 | I49: =I48 -> 0 | ... M49: =M48 -> 0
A51: General Ad Fund7
A52: Advertising and Promotion8
A53: Total Marketing | B53: =SUM(B51:B52) -> 0 | C53: =SUM(C51:C52) -> 0 | D53: =SUM(D51:D52) -> 0 | E53: =SUM(E51:E52) -> 0 | F53: =SUM(F51:F52) -> 0 | G53: =SUM(G51:G52) -> 0 | H53: =SUM(H51:H52) -> 0 | I53: =SUM(I51:I52) -> 0 | ... M53: =SUM(M51:M52) -> 0
A55: Franchise Fee Expense9
A56: Software Fees9
A57: Club Supplies (not for resale)
A58: Uniforms
A59: Bank Service Charges
A60: Dues/Subscriptions10
A61: Legal Fees
A62: Accounting Fees
A63: Telephone Expense
A64: Cable/TV/Internet Service
A65: Cleaning Supplies
A66: Office Supplies
... A70: Gym Equipment Expense12
A71: Total General and Admin | B71: =SUM(B55:B70) -> 0 | C71: =SUM(C55:C70) -> 0 | D71: =SUM(D55:D70) -> 0 | E71: =SUM(E55:E70) -> 0 | F71: =SUM(F55:F70) -> 0 | G71: =SUM(G55:G70) -> 0 | H71: =SUM(H55:H70) -> 0 | I71: =SUM(I55:I70) -> 0 | ... M71: =SUM(M55:M70) -> 0
A73: Total Expenses | B73: =SUM(B71,B53,B49,B46,B39,B34) -> 0 | C73: =SUM(C71,C53,C49,C46,C39,C34) -> 0 | D73: =SUM(D71,D53,D49,D46,D39,D34) -> 0 | E73: =SUM(E71,E53,E49,E46,E39,E34) -> 0 | F73: =SUM(F71,F53,F49,F46,F39,F34) -> 0 | G73: =SUM(G71,G53,G49,G46,G39,G34) -> 0 | H73: =SUM(H71,H53,H49,H46,H39,H34) -> 0 | I73: =SUM(I71,I53,I49,I46,I39,I34) -> 0 | ... M73: =SUM(M71,M53,M49,M46,M39,M34) -> 0
A75: Net Operating Income | B75: =B27-B73 -> 0 | C75: =C27-C73 -> 0 | D75: =D27-D73 -> 0 | E75: =E27-E73 -> 0 | F75: =F27-F73 -> 0 | G75: =G27-G73 -> 0 | H75: =H27-H73 -> 0 | I75: =I27-I73 -> 0 | ... M75: =M27-M73 -> 0
A76: Net Income Margin % | B76: =B75/B11 -> #DIV/0! | C76: =C75/C11 -> #DIV/0! | D76: =D75/D11 -> #DIV/0! | E76: =E75/E11 -> #DIV/0! | F76: =F75/F11 -> #DIV/0! | G76: =G75/G11 -> #DIV/0! | H76: =H75/H11 -> #DIV/0! | I76: =I75/I11 -> #DIV/0! | ... M76: =M75/M11 -> #DIV/0!
A78: Total Other Income | B78: 0 | C78: 0 | D78: 0 | E78: 0 | F78: 0 | G78: 0 | H78: 0 | I78: 0 | J78: 0 | K78: 0 | L78: 0 | M78: 0
A80: Taxes & Licenses13
A81: Interest Expense14
A82: Donations
A83: Total Other Expenses | B83: =SUM(B80:B82) -> 0 | C83: =SUM(C80:C82) -> 0 | D83: =SUM(D80:D82) -> 0 | E83: =SUM(E80:E82) -> 0 | F83: =SUM(F80:F82) -> 0 | G83: =SUM(G80:G82) -> 0 | H83: =SUM(H80:H82) -> 0 | I83: =SUM(I80:I82) -> 0 | ... M83: =SUM(M80:M82) -> 0
A85: Net Income | B85: =B75-B83 -> 0 | C85: =C75-C83 -> 0 | D85: =D75-D83 -> 0 | E85: =E75-E83 -> 0 | F85: =F75-F83 -> 0 | G85: =G75-G83 -> 0 | H85: =H75-H83 -> 0 | I85: =I75-I83 -> 0 | ... M85: =M75-M83 -> 0
A87: Key:
A88: 1. Ancillary Sales - apparel, supplements, tanning, etc
A89: 2. Consumables - cost of good/services such as apparel, supplements, vending. Anything that is being "consumed" by a buyer
A90: 3. Examples of Administrative Fees are if you decide to get multiple deposits from ABC Financial instead of just the twice per month that is the default
A91: 4. Processing Fees - any other fees that ABC charges to process payments
A92: 5. Training/Development - investment back into staff. This would include contributions to a PT certification, an Excel course or another business or fitness related course. Would also include purchase of books for staff to read
A94: 6. If you are spending money on Indeed, ZipRecruiter, or a similar platform for recruiting employees, those expenses would be placed in this section
A95: 7. General Ad Fund - fixed amount that Anytime Fitness Corporate collects for advertising
A96: 8. Advertising and Promotions - spend outside of the General Ad Fund - for more information on the required spend, reference the Resource Center and FDD. For marketing ideas for this category, contact your FBC.
A98: 9. Franchise and Software Fee expenses - fixed amounts charged by Anytime Fitness Corporate
A99: 10. Dues/Subscriptions - includes things like magazines and subscriptions/dues to different industry organizations if applicable
A100: 11. Loan fees - fees outside of the interest and principal. Examples include application, processing, origination, closing annual, late, overdraft, NSF and prepayment fees to name a few.
... A104: 14. Only interest expense is included if you have an SBA loan or another loan for your business. Principal for the loan would not be included in the P&L

Sheet Cash Flow
A1: Insert Year | B1: January | C1: February | D1: March | E1: April | F1: May | G1: June | H1: July | I1: August | J1: September | K1: October | L1: November | M1: December
A2: Net Income
A3: Total Revenue | B3: ='P&L'!B11 -> 0 | C3: ='P&L'!C11 -> 0 | D3: ='P&L'!D11 -> 0 | E3: ='P&L'!E11 -> 0 | F3: ='P&L'!F11 -> 0 | G3: ='P&L'!G11 -> 0 | H3: ='P&L'!H11 -> 0 | I3: ='P&L'!I11 -> 0 | ... M3: ='P&L'!M11 -> 0 | O3: Calculated Cell
A4: Gross Profit1 | B4: ='P&L'!B27 -> 0 | C4: ='P&L'!C27 -> 0 | D4: ='P&L'!D27 -> 0 | E4: ='P&L'!E27 -> 0 | F4: ='P&L'!F27 -> 0 | G4: ='P&L'!G27 -> 0 | H4: ='P&L'!H27 -> 0 | I4: ='P&L'!I27 -> 0 | ... M4: ='P&L'!M27 -> 0 | O4: Input
A5: Gross Profit:Revenue | B5: =IFERROR(B4/B3,0) -> 0 | C5: =IFERROR(C4/C3,0) -> 0 | D5: =IFERROR(D4/D3,0) -> 0 | E5: =IFERROR(E4/E3,0) -> 0 | F5: =IFERROR(F4/F3,0) -> 0 | G5: =IFERROR(G4/G3,0) -> 0 | H5: =IFERROR(H4/H3,0) -> 0 | I5: =IFERROR(I4/I3,0) -> 0 | ... M5: =IFERROR(M4/M3,0) -> 0 | O5: Linked Cell
A6: Total Expenses | B6: ='P&L'!B73 -> 0 | C6: ='P&L'!C73 -> 0 | D6: ='P&L'!D73 -> 0 | E6: ='P&L'!E73 -> 0 | F6: ='P&L'!F73 -> 0 | G6: ='P&L'!G73 -> 0 | H6: ='P&L'!H73 -> 0 | I6: ='P&L'!I73 -> 0 | ... M6: ='P&L'!M73 -> 0
A7: Net Operating Income | B7: =B4-B6 -> 0 | C7: =C4-C6 -> 0 | D7: =D4-D6 -> 0 | E7: =E4-E6 -> 0 | F7: =F4-F6 -> 0 | G7: =G4-G6 -> 0 | H7: =H4-H6 -> 0 | I7: =I4-I6 -> 0 | ... M7: =M4-M6 -> 0
A8: Interest Expense | B8: ='P&L'!B81 -> 0 | C8: ='P&L'!C81 -> 0 | D8: ='P&L'!D81 -> 0 | E8: ='P&L'!E81 -> 0 | F8: ='P&L'!F81 -> 0 | G8: ='P&L'!G81 -> 0 | H8: ='P&L'!H81 -> 0 | I8: ='P&L'!I81 -> 0 | ... M8: ='P&L'!M81 -> 0
A9: Holding Co Salaries2
A10: Holding Co Operating Expenses3
A11: Total Other Expenses | B11: =SUM(B8:B10) -> 0 | C11: =SUM(C8:C10) -> 0 | D11: =SUM(D8:D10) -> 0 | E11: =SUM(E8:E10) -> 0 | F11: =SUM(F8:F10) -> 0 | G11: =SUM(G8:G10) -> 0 | H11: =SUM(H8:H10) -> 0 | I11: =SUM(I8:I10) -> 0 | ... M11: =SUM(M8:M10) -> 0
A12: Net Income | B12: =B7-B11 -> 0 | C12: =C7-C11 -> 0 | D12: =D7-D11 -> 0 | E12: =E7-E11 -> 0 | F12: =F7-F11 -> 0 | G12: =G7-G11 -> 0 | H12: =H7-H11 -> 0 | I12: =I7-I11 -> 0 | ... M12: =M7-M11 -> 0
A13: Net Income:Revenue4 | B13: =IFERROR(B12/B3,0) -> 0 | C13: =IFERROR(C12/C3,0) -> 0 | D13: =IFERROR(D12/D3,0) -> 0 | E13: =IFERROR(E12/E3,0) -> 0 | F13: =IFERROR(F12/F3,0) -> 0 | G13: =IFERROR(G12/G3,0) -> 0 | H13: =IFERROR(H12/H3,0) -> 0 | I13: =IFERROR(I12/I3,0) -> 0 | ... M13: =IFERROR(M12/M3,0) -> 0
A15: Other Cash Outflow
A16: SBA Loan Principal5
A17: Investor Principal6
A18: Total Other Cash Outflow | B18: =SUM(B16:B17) -> 0 | C18: =SUM(C16:C17) -> 0 | D18: =SUM(D16:D17) -> 0 | E18: =SUM(E16:E17) -> 0 | F18: =SUM(F16:F17) -> 0 | G18: =SUM(G16:G17) -> 0 | H18: =SUM(H16:H17) -> 0 | I18: =SUM(I16:I17) -> 0 | ... M18: =SUM(M16:M17) -> 0
A19: CashFlow | B19: =B12-B18 -> 0 | C19: =C12-C18 -> 0 | D19: =D12-D18 -> 0 | E19: =E12-E18 -> 0 | F19: =F12-F18 -> 0 | G19: =G12-G18 -> 0 | H19: =H12-H18 -> 0 | I19: =I12-I18 -> 0 | ... M19: =M12-M18 -> 0
A20: Owner Distribution7 | B20: 0
A21: Free Cashflow | B21: =B19-B20 -> 0 | C21: =C19-C20 -> 0 | D21: =D19-D20 -> 0 | E21: =E19-E20 -> 0 | F21: =F19-F20 -> 0 | G21: =G19-G20 -> 0 | H21: =H19-H20 -> 0 | I21: =I19-I20 -> 0 | ... M21: =M19-M20 -> 0
A24: Key
A25: 1. Including the Gross Profit to Revenue is optional, but recommended. It is calculated by taking the Gross Profit and dividing it by the Revenue
A26: 2. Holding Co Salaries - salary that is paid out for your holding company specifically. Where the owner's salary would be placed
A27: 3. Holding Co Operating Expenses - expenses that correspond specifically to the holding company, but not necessarily the Anytime Fitness Club.
A28: An assistant or health insurance would be examples included here
A29: 4. Looking at the ratio of Net Income to Revenue is optional, but recommended. This is calculation by taking the Net Income and dividing it by the Revenue
A30: 5. This is only listing the Principal of the SBA loan. Interest is pulled from the P&L statement and is included in the Interest Expense section above
A31: 6. If you have outside investors, the principal payment to these investors would be included here
A32: 7. If there is still cashflow remaining when all expenses are paid and you choose to distribute funds to the owner group, this would be included here
