Workbook

Sheet Coaching Proforma
B1: AF Training Proforma | F1: *All sessions 60 minutes *4.3 weeks per month *2 visits per week average per client
B2: Insert data into double red cells.
B4: 15 | C4: 20 | D4: 30 | E4: 40 | F4: 60 | H4: Small Group Training | I4: Team Workouts
B5: Functional Space Square Footage | F5: =D5/75 -> 0 | G5: Percentage Capacity | H5: =D10/D8 -> 0 | I5: =E10/E8 -> #DIV/0!
B7: Recommendations | C7: One-on-One Training | D7: Small Group Training | E7: Team Workouts | G7: Monthly Department P&L Summary | K7: Annual Department P&L Summary
B8: Capacity Reccomendation | C8: 1 | D8: 4 | E8: =IF(F5<8,"0",IF(F5>=8,F5)) -> 0 | G8: Revenue | H8: Payroll | I8: Client Count | J8: Monthly Profit | K8: Revenue | L8: Payroll | M8: Gross Profit Margins | N8: Gross Profit
B9: Pricing Reccomendation | C9: 60 | D9: =IF(D5<=599, D4, IF(AND(D5>=600,D5<=899), E4, IF(D5>=900,D4))) -> 30 | E9: =IF(D5<=599, "0", IF(AND(D5>=600,D5<=899), C4, IF(D5>=900,B4))) -> 0 | G9: =SUM(L25:L29) -> 0 | H9: =SUM(M25:M29) -> 0 | I9: =F21+I21+L21 -> 0 | J9: =G9-H9 -> 0 | K9: =G9*12 -> 0 | L9: =H9*12 -> 0 | M9: =(K9-L9)/K9 -> #DIV/0! | N9: =K9-L9 -> 0
B10: Actual Session size
B11: Pricing
C13: Weekly
A14: Weekly | C14: Shift | F14: One-on-One Training | I14: Small Group Training | L14: Team Workouts
C15: Hourly Wage | D15: Total Hours | E15: Base Compensation | F15: One-on-One Compensation | G15: One-on-One Serviced | H15: One-on-One Compensation | I15: SGT Session Compensation | J15: SGT Sessions Serviced | K15: SGT Compensation | L15: Team Session Compensation | M15: Team Sessions Serviced | N15: Team Compensation
B16: MXM | E16: =D16*C16 -> 0 | H16: =F16*G16 -> 0 | K16: =I16*J16 -> 0 | N16: =L16*M16 -> 0
B17: Coach 1 | E17: =D17*C17 -> 0 | H17: =F17*G17 -> 0 | K17: =I17*J17 -> 0 | N17: =L17*M17 -> 0
B18: Coach 2 | E18: =D18*C18 -> 0 | H18: =F18*G18 -> 0 | K18: =I18*J18 -> 0 | N18: =L18*M18 -> 0
B19: Coach 3 | E19: =D19*C19 -> 0 | H19: =F19*G19 -> 0 | K19: =I19*J19 -> 0 | N19: =L19*M19 -> 0
B20: Coach 4 | E20: =D20*C20 -> 0 | H20: =F20*G20 -> 0 | K20: =I20*J20 -> 0 | N20: =L20*M20 -> 0
F21: =(SUM(G16:G20))/2 -> 0 | G21: PT Clients | I21: =((SUM(J16:J20))*D10)/2 -> 0 | J21: SGT Clients | L21: =((SUM(M16:M20))*E10)/2 -> 0 | M21: Team Clients
C22: Monthly
A23: Monthly | C23: Revenue Generated | F23: Bonus/Commisions Pay | I23: Total Compensation | L23: Staff P&L Summary
C24: One-on-One Training | D24: Small Group Training | E24: Team Workouts | F24: Individual Gross Percentage | G24: Department Gross Percentage | H24: Commission Compensation | I24: Average Hourly | J24: Total Monthly | K24: Total Annual | L24: Revenue | M24: Payroll | N24: Gross Profit Margins
B25: MXM | C25: =(G16*$C$11)*4.3 -> 0 | D25: =((J16*$D$11)*$D$10)*4.3 -> 0 | E25: =((M16*$E$11)*$E$10)*4.3 -> 0 | H25: =(F25*L25)+(G25*G9) -> 0 | I25: =J25/(D16*4.3) -> #DIV/0! | J25: =((E16+H16+K16+N16)*4.3)+H25 -> 0 | K25: =J25*12 -> 0 | L25: =C25+D25+E25 -> 0 | M25: =J25 -> 0 | N25: =(L25-M25)/L25 -> #DIV/0!
B26: Coach 1 | C26: =(G17*$C$11)*4.3 -> 0 | D26: =((J17*$D$11)*$D$10)*4.3 -> 0 | E26: =((M17*$E$11)*$E$10)*4.3 -> 0 | H26: =(F26*L26)+(G26*L26) -> 0 | I26: =J26/(D17*4.3) -> #DIV/0! | J26: =((E17+H17+K17+N17)*4.3)+H26 -> 0 | K26: =J26*12 -> 0 | L26: =C26+D26+E26 -> 0 | M26: =J26 -> 0 | N26: =(L26-M26)/L26 -> #DIV/0!
B27: Coach 2 | C27: =(G18*$C$11)*4.3 -> 0 | D27: =((J18*$D$11)*$D$10)*4.3 -> 0 | E27: =((M18*$E$11)*$E$10)*4.3 -> 0 | H27: =(F27*L27)+(G27*L27) -> 0 | I27: =J27/(D18*4.3) -> #DIV/0! | J27: =((E18+H18+K18+N18)*4.3)+H27 -> 0 | K27: =J27*12 -> 0 | L27: =C27+D27+E27 -> 0 | M27: =J27 -> 0 | N27: =(L27-M27)/L27 -> #DIV/0!
B28: Coach 3 | C28: =(G19*$C$11)*4.3 -> 0 | D28: =((J19*$D$11)*$D$10)*4.3 -> 0 | E28: =((M19*$E$11)*$E$10)*4.3 -> 0 | H28: =(F28*L28)+(G28*L28) -> 0 | I28: =J28/(D19*4.3) -> #DIV/0! | J28: =((E19+H19+K19+N19)*4.3)+H28 -> 0 | K28: =J28*12 -> 0 | L28: =C28+D28+E28 -> 0 | M28: =J28 -> 0 | N28: =(L28-M28)/L28 -> #DIV/0!
B29: Coach 4 | C29: =(G20*$C$11)*4.3 -> 0 | D29: =((J20*$D$11)*$D$10)*4.3 -> 0 | E29: =((M20*$E$11)*$E$10)*4.3 -> 0 | H29: =(F29*L29)+(G29*L29) -> 0 | I29: =J29/(D20*4.3) -> #DIV/0! | J29: =((E20+H20+K20+N20)*4.3)+H29 -> 0 | K29: =J29*12 -> 0 | L29: =C29+D29+E29 -> 0 | M29: =J29 -> 0 | N29: =(L29-M29)/L29 -> #DIV/0!
M30: =SUM(M25:M29) -> 0
B32: “This proforma is being provided to you as a franchisee in the Anytime Fitness system. It is intended as a tool to assist you in evaluating your personal training programming, however we make no warranty regarding any particular results or accuracy of the information herein. Anytime Fitness, LLC does not provide or recommend revenue estimates or cost assumptions for your club, nor do we recommend particular compensation or other employment terms for your personnel. Once you make your own assumptions, the proforma populates the various columns using your assumptions. You may wish to consult with an accountant or other personal advisor to assist you in completing this proforma, and in analyzing any results produced.”

Sheet Small Group KPIs
A1: Launch Goals
A2: Weekly SGT Sessions | B2: Paid Trials Count Goal | C2: Paid Trial Cost | D2: Launch TE to Long term PT % | E2: New Client Count | F2: New Avg PT Month Package Value | G2: Projected Draft Added
A3: ='Coaching Proforma'!J16+'Coaching Proforma'!J17+'Coaching Proforma'!J18+'Coaching Proforma'!J19+'Coaching Proforma'!J20 -> 0 | B3: =(A3*'Coaching Proforma'!D10)/2 -> 0 | E3: =D3*B3 -> 0 | F3: ='Coaching Proforma'!D11*8 -> 0 | G3: =E3*F3 -> 0
A5: KPI Goal Month 1
A6: Average Monthly New Members | B6: FCs @ POS % | C6: FC Booked at POS | D6: Floor Pulls | E6: FC Show % | F6: FC Show | G6: Long Term Agreement Close % | H6: New Long Term PT Agreements | I6: TE Agreement Close % | J6: TE Agreement | K6: Current TEs | L6: TE Closed to Long Term Agreement % | M6: TE Closed to Long Term Agreement | N6: Projected Draft Added | O6: Total Draft | P6: % to revenue goal
C7: =B7*A7 -> 0 | F7: =(C7+D7)*E7 -> 0 | H7: =F7*G7 -> 0 | J7: =F7*I7 -> 0 | K7: =B3 -> 0 | L7: =D3 -> 0 | M7: =K7*L7 -> 0 | N7: =(H7*F3)+(M7*F3) -> 0 | O7: =N7 -> 0 | P7: =N7/SUM('Coaching Proforma'!D25:D29) -> #DIV/0!
A9: KPI Goal Month 2
A10: Average Monthly New Members | B10: FCs @ POS % | C10: FC Booked at POS | D10: Floor Pulls | E10: FC Show % | F10: FC Show | G10: Long Term Agreement Close % | H10: New Long Term PT Agreements | I10: TE Agreement Close % | J10: TE Agreement | K10: Current TEs | L10: TE Closed to Long Term Agreement % | M10: TE Closed to Long Term Agreement | N10: Projected Draft Added | O10: Total Draft | P10: % to revenue goal
C11: =B11*A11 -> 0 | F11: =(C11+D11)*E11 -> 0 | H11: =F11*G11 -> 0 | J11: =F11*I11 -> 0 | K11: =J7 -> 0 | M11: =K11*L11 -> 0 | N11: =(H11*F3)+(M11*F3) -> 0 | O11: =N7+N11 -> 0 | P11: =O11/SUM('Coaching Proforma'!D25:D29) -> #DIV/0!
A13: KPI Goal Month 3
A14: Average Monthly New Members | B14: FCs @ POS % | C14: FC Booked at POS | D14: Floor Pulls | E14: FC Show % | F14: FC Show | G14: Long Term Agreement Close % | H14: New Long Term PT Agreements | I14: TE Agreement Close % | J14: TE Agreement | K14: Current TEs | L14: TE Closed to Long Term Agreement % | M14: TE Closed to Long Term Agreement | N14: Projected Draft Added | O14: Total Draft | P14: % to revenue goal
C15: =B15*A15 -> 0 | F15: =(C15+D15)*E15 -> 0 | H15: =F15*G15 -> 0 | J15: =F15*I15 -> 0 | K15: =J11 -> 0 | M15: =K15*L15 -> 0 | N15: =(H15*F3)+(M15*F3) -> 0 | O15: =O11+N15 -> 0 | P15: =O15/SUM('Coaching Proforma'!$D$25:$D$29) -> #DIV/0!
A17: KPI Goal Month 4
A18: Average Monthly New Members | B18: FCs @ POS % | C18: FC Booked at POS | D18: Floor Pulls | E18: FC Show % | F18: FC Show | G18: Long Term Agreement Close % | H18: New Long Term PT Agreements | I18: TE Agreement Close % | J18: TE Agreement | K18: Current TEs | L18: TE Closed to Long Term Agreement % | M18: TE Closed to Long Term Agreement | N18: Projected Draft Added | O18: Total Draft | P18: % to revenue goal
C19: =B19*A19 -> 0 | F19: =(C19+D19)*E19 -> 0 | H19: =F19*G19 -> 0 | J19: =F19*I19 -> 0 | K19: =J15 -> 0 | M19: =K19*L19 -> 0 | N19: =(H19*F3)+(M19*F3) -> 0 | O19: =O15+N19 -> 0 | P19: =O19/SUM('Coaching Proforma'!$D$25:$D$29) -> #DIV/0!
A21: KPI Goal Month 5
A22: Average Monthly New Members | B22: FCs @ POS % | C22: FC Booked at POS | D22: Floor Pulls | E22: FC Show % | F22: FC Show | G22: Long Term Agreement Close % | H22: New Long Term PT Agreements | I22: TE Agreement Close % | J22: TE Agreement | K22: Current TEs | L22: TE Closed to Long Term Agreement % | M22: TE Closed to Long Term Agreement | N22: Projected Draft Added | O22: Total Draft | P22: % to revenue goal
C23: =B23*A23 -> 0 | F23: =(C23+D23)*E23 -> 0 | H23: =F23*G23 -> 0 | J23: =F23*I23 -> 0 | K23: =J19 -> 0 | M23: =K23*L23 -> 0 | N23: =(H23*F3)+(M23*F3) -> 0 | O23: =O19+N23 -> 0 | P23: =O23/SUM('Coaching Proforma'!$D$25:$D$29) -> #DIV/0!
A25: KPI Goal Month 6
A26: Average Monthly New Members | B26: FCs @ POS % | C26: FC Booked at POS | D26: Floor Pulls | E26: FC Show % | F26: FC Show | G26: Long Term Agreement Close % | H26: New Long Term PT Agreements | I26: TE Agreement Close % | J26: TE Agreement | K26: Current TEs | L26: TE Closed to Long Term Agreement % | M26: TE Closed to Long Term Agreement | N26: Projected Draft Added | O26: Total Draft | P26: % to revenue goal
C27: =B27*A27 -> 0 | F27: =(C27+D27)*E27 -> 0 | H27: =F27*G27 -> 0 | J27: =F27*I27 -> 0 | K27: =J23 -> 0 | M27: =K27*L27 -> 0 | N27: =(H27*F3)+(M27*F3) -> 0 | O27: =O23+N27 -> 0 | P27: =O27/SUM('Coaching Proforma'!$D$25:$D$29) -> #DIV/0!

Sheet Team Training KPIs
A1: Launch Goals
A2: Weekly Team Sessions | B2: Paid Trials Count Goal | C2: Paid Trial Cost | D2: Launch TE to Long term PT % | E2: New Client Count | F2: New Avg PT Month Package Value | G2: Projected Draft Added
A3: =SUM('Coaching Proforma'!M16:M20) -> 0 | B3: =(A3*'Coaching Proforma'!E10)/2 -> 0 | E3: =D3*B3 -> 0 | F3: ='Coaching Proforma'!E11*8 -> 0 | G3: =E3*F3 -> 0
A5: KPI Goal Month 1
A6: Average Monthly New Members | B6: FCs @ POS % | C6: FC Booked at POS | D6: Floor Pulls | E6: FC Show % | F6: FC Show | G6: Long Term Agreement Close % | H6: New Long Term PT Agreements | I6: TE Agreement Close % | J6: TE Agreement | K6: Current TEs | L6: TE Closed to Long Term Agreement % | M6: TE Closed to Long Term Agreement | N6: Projected Draft Added | O6: Total Draft | P6: % to goal
C7: =B7*A7 -> 0 | F7: =(C7+D7)*E7 -> 0 | H7: =F7*G7 -> 0 | J7: =F7*I7 -> 0 | K7: =B3 -> 0 | L7: =D3 -> 0 | M7: =K7*L7 -> 0 | N7: =(H7*F3)+(M7*F3) -> 0 | O7: =N7 -> 0 | P7: =N7/SUM('Coaching Proforma'!E25:E29) -> #DIV/0!
A9: KPI Goal Month 2
A10: Average Monthly New Members | B10: FCs @ POS % | C10: FC Booked at POS | D10: Floor Pulls | E10: FC Show % | F10: FC Show | G10: Long Term Agreement Close % | H10: New Long Term PT Agreements | I10: TE Agreement Close % | J10: TE Agreement | K10: Current TEs | L10: TE Closed to Long Term Agreement % | M10: TE Closed to Long Term Agreement | N10: Projected Draft Added | O10: Total Draft | P10: % to goal
C11: =B11*A11 -> 0 | F11: =(C11+D11)*E11 -> 0 | H11: =F11*G11 -> 0 | J11: =F11*I11 -> 0 | K11: =J7 -> 0 | M11: =K11*L11 -> 0 | N11: =(H11*F3)+(M11*F3) -> 0 | O11: =N7+N11 -> 0 | P11: =O11/SUM('Coaching Proforma'!E25:E29) -> #DIV/0!
A13: KPI Goal Month 3
A14: Average Monthly New Members | B14: FCs @ POS % | C14: FC Booked at POS | D14: Floor Pulls | E14: FC Show % | F14: FC Show | G14: Long Term Agreement Close % | H14: New Long Term PT Agreements | I14: TE Agreement Close % | J14: TE Agreement | K14: Current TEs | L14: TE Closed to Long Term Agreement % | M14: TE Closed to Long Term Agreement | N14: Projected Draft Added | O14: Total Draft | P14: % to goal
C15: =B15*A15 -> 0 | F15: =(C15+D15)*E15 -> 0 | H15: =F15*G15 -> 0 | J15: =F15*I15 -> 0 | K15: =J11 -> 0 | M15: =K15*L15 -> 0 | N15: =(H15*F3)+(M15*F3) -> 0 | O15: =O11+N15 -> 0 | P15: =O15/SUM('Coaching Proforma'!$E$25:$E$29) -> #DIV/0!
A17: KPI Goal Month 4
A18: Average Monthly New Members | B18: FCs @ POS % | C18: FC Booked at POS | D18: Floor Pulls | E18: FC Show % | F18: FC Show | G18: Long Term Agreement Close % | H18: New Long Term PT Agreements | I18: TE Agreement Close % | J18: TE Agreement | K18: Current TEs | L18: TE Closed to Long Term Agreement % | M18: TE Closed to Long Term Agreement | N18: Projected Draft Added | O18: Total Draft | P18: % to goal
C19: =B19*A19 -> 0 | F19: =(C19+D19)*E19 -> 0 | H19: =F19*G19 -> 0 | J19: =F19*I19 -> 0 | K19: =J15 -> 0 | M19: =K19*L19 -> 0 | N19: =(H19*F3)+(M19*F3) -> 0 | O19: =O15+N19 -> 0 | P19: =O19/SUM('Coaching Proforma'!$E$25:$E$29) -> #DIV/0!
A21: KPI Goal Month 5
A22: Average Monthly New Members | B22: FCs @ POS % | C22: FC Booked at POS | D22: Floor Pulls | E22: FC Show % | F22: FC Show | G22: Long Term Agreement Close % | H22: New Long Term PT Agreements | I22: TE Agreement Close % | J22: TE Agreement | K22: Current TEs | L22: TE Closed to Long Term Agreement % | M22: TE Closed to Long Term Agreement | N22: Projected Draft Added | O22: Total Draft | P22: % to goal
C23: =B23*A23 -> 0 | F23: =(C23+D23)*E23 -> 0 | H23: =F23*G23 -> 0 | J23: =F23*I23 -> 0 | K23: =J19 -> 0 | M23: =K23*L23 -> 0 | N23: =(H23*F3)+(M23*F3) -> 0 | O23: =O19+N23 -> 0 | P23: =O23/SUM('Coaching Proforma'!$E$25:$E$29) -> #DIV/0!
A25: KPI Goal Month 6
A26: Average Monthly New Members | B26: FCs @ POS % | C26: FC Booked at POS | D26: Floor Pulls | E26: FC Show % | F26: FC Show | G26: Long Term Agreement Close % | H26: New Long Term PT Agreements | I26: TE Agreement Close % | J26: TE Agreement | K26: Current TEs | L26: TE Closed to Long Term Agreement % | M26: TE Closed to Long Term Agreement | N26: Projected Draft Added | O26: Total Draft | P26: % to goal
C27: =B27*A27 -> 0 | F27: =(C27+D27)*E27 -> 0 | H27: =F27*G27 -> 0 | J27: =F27*I27 -> 0 | K27: =J23 -> 0 | M27: =K27*L27 -> 0 | N27: =(H27*F3)+(M27*F3) -> 0 | O27: =O23+N27 -> 0 | P27: =O27/SUM('Coaching Proforma'!$E$25:$E$29) -> #DIV/0!
