Workbook
Name RENT: Input!$C$18

Sheet Macro1

Sheet Input
A1: ENTER MONTHLY EXPENSE AMOUNTS BELOW BASED ON CURRENT PROFIT AND LOSS DATA PROVIDED BY THE SELLER OF THE CLUB
A4: Operating Expenses
A5: Payroll Expenses | C5: =SUM(C6:C9) -> 0
B6: Payroll
B7: Payroll - Taxes
B8: Payroll - Benefits
B9: Travel & Entertainment
A10: Franchise Expenses | C10: =SUM(C11:C13) -> 0
B11: Royalty Payments
B12: Software Support
B13: General Ad Fund | D13: **$600 max per 2019 FDD
A14: Advertising/Marketing | C14: =SUM(C15:C16) -> 0
B15: Advertising/Marketing
B16: Postage
A17: Property Expenses | C17: =SUM(C18:C22) -> 0
B18: Rent
B19: Taxes - Property
B20: Utilities (Trash/Water/Electric/Gas)
B21: Telephone
B22: Internet/Cable
A23: Professional Expenses | C23: =SUM(C24:C25) -> 0
B24: Insurance
B25: Legal & Accounting
A26: Misc Expenses | C26: =SUM(C27:C36) -> 0
B27: Bank Fees
B28: Credit Card Fees
B29: Dues and Subscriptions
B30: Equipment Expense
B31: Office Supplies
B32: Repairs & Maint
B33: <Enter>
B34: <Enter>
B35: <Enter>
B36: <Enter>
C37: =C5+C10+C14+C17+C23+C26 -> 0

Sheet AF Projections
A1: Anytime Fitness Full Size Unit Pro Forma Calculator **Please See Footnotes Below Prior to Starting Exercise**
A2: This calculator is provided in blank to prospective franchisees of Anytime Fitness. All revenues and expense assumptions must be completed by prospective franchisees.
A5: Membership Data Assumptions
A6: % of PPV Accounts
A7: Acquired PPV Accounts
A8: Acquired Single Members
A9: Enrollment fee
A10: Average Member Fee
A11: Average PPV Fee
A13: Attrition Rate
A16: Other Income Assumptions
A17: Personal Training Income/Member
... A28: Expense Assumptions (ENTER IN INPUT TAB)
A29: Rent | B29: =RENT -> 0
A30: Monthly Franchise Fee | B30: =Input!C11 -> 0
A31: Base Technology Fee | B31: =Input!C12 -> 0
A32: General Advertising Fee | B32: =Input!C13 -> 0
A33: Advertising (Local) | B33: =Input!C14 -> 0
A34: Payroll | B34: =Input!C5 -> 0
A35: Utilities | B35: =SUM(Input!C20:C22) -> 0
A36: Property Taxes | B36: =Input!C19 -> 0
A37: Insurance | B37: =Input!C24 -> 0
A38: Professional Fees | B38: =Input!C25 -> 0
A39: Bank/CC Fees | B39: =Input!C27+Input!C28 -> 0
A40: Supplies | B40: =Input!C29+Input!C30+Input!C31 -> 0
A41: Maintenace | B41: =Input!C32 -> 0
A42: Miscellaneous | B42: =SUM(Input!C33:C36) -> 0
A43: Bad Debt Percentage
A46: # of months Rent Abatement
A49: NOTE: All information contained in this document is for example only. Revenue and expense figures may vary significantly based on numerous factors.
A51: YEAR 1 | B51: Beginning Balance | C51: Month 1 | D51: Month2 | E51: Month3 | F51: Month 4 | G51: Month 5 | H51: Month 6 | I51: Month 7 | J51: Month 8 | K51: Month 9 | L51: Month 10 | M51: Month 11 | N51: Month 12
A52: Monthly New Members
A53: (6) Single Members | B53: 0 | C53: =ROUND((C52*(1-$B$6)),0) -> 0 | D53: =ROUND((D52*(1-$B$6)),0) -> 0 | E53: =ROUND((E52*(1-$B$6)),0) -> 0 | F53: =ROUND((F52*(1-$B$6)),0) -> 0 | G53: =ROUND((G52*(1-$B$6)),0) -> 0 | H53: =ROUND((H52*(1-$B$6)),0) -> 0 | I53: =ROUND((I52*(1-$B$6)),0) -> 0 | J53: =ROUND((J52*(1-$B$6)),0) -> 0 | ... N53: =ROUND((N52*(1-$B$6)),0) -> 0
A54: Member Attrition | B54: 0 | C54: =-B55*($B$13/12) -> 0 | D54: =-C55*($B$13/12) -> 0 | E54: =-D55*($B$13/12) -> 0 | F54: =-E55*($B$13/12) -> 0 | G54: =-F55*($B$13/12) -> 0 | H54: =-G55*($B$13/12) -> 0 | I54: =-H55*($B$13/12) -> 0 | J54: =-I55*($B$13/12) -> 0 | ... N54: =-M55*($B$13/12) -> 0
A55: Accumulated Single Members | B55: =B8 -> 0 | C55: =B55+C53+C54 -> 0 | D55: =C55+D53+D54 -> 0 | E55: =D55+E53+E54 -> 0 | F55: =E55+F53+F54 -> 0 | G55: =F55+G53+G54 -> 0 | H55: =G55+H53+H54 -> 0 | I55: =H55+I53+I54 -> 0 | J55: =I55+J53+J54 -> 0 | ... N55: =M55+N53+N54 -> 0
A56: Pay Per Visit "PPV" Members | B56: 0 | C56: =ROUND(C52*$B$6,0) -> 0 | D56: =ROUND(D52*$B$6,0) -> 0 | E56: =ROUND(E52*$B$6,0) -> 0 | F56: =ROUND(F52*$B$6,0) -> 0 | G56: =ROUND(G52*$B$6,0) -> 0 | H56: =ROUND(H52*$B$6,0) -> 0 | I56: =ROUND(I52*$B$6,0) -> 0 | J56: =ROUND(J52*$B$6,0) -> 0 | ... N56: =ROUND(N52*$B$6,0) -> 0
A57: PPV Attrition | B57: 0 | C57: =-B58*($B$13/12) -> 0 | D57: =-C58*($B$13/12) -> 0 | E57: =-D58*($B$13/12) -> 0 | F57: =-E58*($B$13/12) -> 0 | G57: =-F58*($B$13/12) -> 0 | H57: =-G58*($B$13/12) -> 0 | I57: =-H58*($B$13/12) -> 0 | J57: =-I58*($B$13/12) -> 0 | ... N57: =-M58*($B$13/12) -> 0
A58: Accumulated PPV Members | B58: =B7 -> 0 | C58: =B58+C56+C57 -> 0 | D58: =C58+D56+D57 -> 0 | E58: =D58+E56+E57 -> 0 | F58: =E58+F56+F57 -> 0 | G58: =F58+G56+G57 -> 0 | H58: =G58+H56+H57 -> 0 | I58: =H58+I56+I57 -> 0 | J58: =I58+J56+J57 -> 0 | ... N58: =M58+N56+N57 -> 0
A59: Accumulating Total Members | B59: =B55+B58 -> 0 | C59: =C58+C55 -> 0 | D59: =D58+D55 -> 0 | E59: =E58+E55 -> 0 | F59: =F58+F55 -> 0 | G59: =G58+G55 -> 0 | H59: =H58+H55 -> 0 | I59: =I58+I55 -> 0 | J59: =J58+J55 -> 0 | ... N59: =N58+N55 -> 0
A60: Recur Single Memb Rev | C60: =C55*$B$10 -> 0 | D60: =D55*$B$10 -> 0 | E60: =E55*$B$10 -> 0 | F60: =F55*$B$10 -> 0 | G60: =G55*$B$10 -> 0 | H60: =H55*$B$10 -> 0 | I60: =I55*$B$10 -> 0 | J60: =J55*$B$10 -> 0 | ... N60: =N55*$B$10 -> 0
A61: Down Payment at Club | C61: =(C58*$B$11) -> 0 | D61: =(D58*$B$11) -> 0 | E61: =(E58*$B$11) -> 0 | F61: =(F58*$B$11) -> 0 | G61: =(G58*$B$11) -> 0 | H61: =(H58*$B$11) -> 0 | I61: =(I58*$B$11) -> 0 | J61: =(J58*$B$11) -> 0 | ... N61: =(N58*$B$11) -> 0
A62: Total Membership Rev | C62: =SUM(C60:C61) -> 0 | D62: =SUM(D60:D61) -> 0 | E62: =SUM(E60:E61) -> 0 | F62: =SUM(F60:F61) -> 0 | G62: =SUM(G60:G61) -> 0 | H62: =SUM(H60:H61) -> 0 | I62: =SUM(I60:I61) -> 0 | J62: =SUM(J60:J61) -> 0 | ... N62: =SUM(N60:N61) -> 0
A63: Vending/Misc Revenues | C63: =(+C59*$B$18)+(C59*$B$19)+(C59*$B$20) -> 0 | D63: =(+D59*$B$18)+(D59*$B$19)+(D59*$B$20) -> 0 | E63: =(+E59*$B$18)+(E59*$B$19)+(E59*$B$20) -> 0 | F63: =(+F59*$B$18)+(F59*$B$19)+(F59*$B$20) -> 0 | G63: =(+G59*$B$18)+(G59*$B$19)+(G59*$B$20) -> 0 | H63: =(+H59*$B$18)+(H59*$B$19)+(H59*$B$20) -> 0 | I63: =(+I59*$B$18)+(I59*$B$19)+(I59*$B$20) -> 0 | J63: =(+J59*$B$18)+(J59*$B$19)+(J59*$B$20) -> 0 | ... N63: =(+N59*$B$18)+(N59*$B$19)+(N59*$B$20) -> 0
A64: Personal Training Revenues | C64: =C59*$B$17 -> 0 | D64: =D59*$B$17 -> 0 | E64: =E59*$B$17 -> 0 | F64: =F59*$B$17 -> 0 | G64: =G59*$B$17 -> 0 | H64: =H59*$B$17 -> 0 | I64: =I59*$B$17 -> 0 | J64: =J59*$B$17 -> 0 | ... N64: =N59*$B$17 -> 0
A65: Enrollment Fees | B65: =B52*$B$9 -> 0 | C65: =C52*$B$9 -> 0 | D65: =D52*$B$9 -> 0 | E65: =E52*$B$9 -> 0 | F65: =F52*$B$9 -> 0 | G65: =G52*$B$9 -> 0 | H65: =H52*$B$9 -> 0 | I65: =I52*$B$9 -> 0 | ... N65: =N52*$B$9 -> 0
A66: Total Revenues | B66: =SUM(B62:B65) -> 0 | C66: =SUM(C62:C65) -> 0 | D66: =SUM(D62:D65) -> 0 | E66: =SUM(E62:E65) -> 0 | F66: =SUM(F62:F65) -> 0 | G66: =SUM(G62:G65) -> 0 | H66: =SUM(H62:H65) -> 0 | I66: =SUM(I62:I65) -> 0 | ... N66: =SUM(N62:N65) -> 0
A67: Payment processing | C67: =(C62*0.05)+((C65+C64)*0.015) -> 0 | D67: =(D62*0.05)+((D65+D64)*0.015) -> 0 | E67: =(E62*0.05)+((E65+E64)*0.015) -> 0 | F67: =(F62*0.05)+((F65+F64)*0.015) -> 0 | G67: =(G62*0.05)+((G65+G64)*0.015) -> 0 | H67: =(H62*0.05)+((H65+H64)*0.015) -> 0 | I67: =(I62*0.05)+((I65+I64)*0.015) -> 0 | J67: =(J62*0.05)+((J65+J64)*0.015) -> 0 | ... N67: =(N62*0.05)+((N65+N64)*0.015) -> 0
A68: Proximity Cards | C68: =C52*$B$25 -> 0 | D68: =D52*$B$25 -> 0 | E68: =E52*$B$25 -> 0 | F68: =F52*$B$25 -> 0 | G68: =G52*$B$25 -> 0 | H68: =H52*$B$25 -> 0 | I68: =I52*$B$25 -> 0 | J68: =J52*$B$25 -> 0 | ... N68: =N52*$B$25 -> 0
A69: Vending Costs | C69: =($B$18*C59)*$B$23 -> 0 | D69: =($B$18*D59)*$B$23 -> 0 | E69: =($B$18*E59)*$B$23 -> 0 | F69: =($B$18*F59)*$B$23 -> 0 | G69: =($B$18*G59)*$B$23 -> 0 | H69: =($B$18*H59)*$B$23 -> 0 | I69: =($B$18*I59)*$B$23 -> 0 | J69: =($B$18*J59)*$B$23 -> 0 | ... N69: =($B$18*N59)*$B$23 -> 0
A70: Personal Training Commissions | C70: =C64*$B$24 -> 0 | D70: =D64*$B$24 -> 0 | E70: =E64*$B$24 -> 0 | F70: =F64*$B$24 -> 0 | G70: =G64*$B$24 -> 0 | H70: =H64*$B$24 -> 0 | I70: =I64*$B$24 -> 0 | J70: =J64*$B$24 -> 0 | ... N70: =N64*$B$24 -> 0
A71: Total COGS | B71: =SUM(B67:B70) -> 0 | C71: =SUM(C67:C70) -> 0 | D71: =SUM(D67:D70) -> 0 | E71: =SUM(E67:E70) -> 0 | F71: =SUM(F67:F70) -> 0 | G71: =SUM(G67:G70) -> 0 | H71: =SUM(H67:H70) -> 0 | I71: =SUM(I67:I70) -> 0 | ... N71: =SUM(N67:N70) -> 0
A72: Gross Profit | B72: =B66-B71 -> 0 | C72: =C66-C71 -> 0 | D72: =D66-D71 -> 0 | E72: =E66-E71 -> 0 | F72: =F66-F71 -> 0 | G72: =G66-G71 -> 0 | H72: =H66-H71 -> 0 | I72: =I66-I71 -> 0 | ... N72: =N66-N71 -> 0
A73: Payroll & Employee Expenses | C73: =$B$34 -> 0 | D73: =$B$34 -> 0 | E73: =$B$34 -> 0 | F73: =$B$34 -> 0 | G73: =$B$34 -> 0 | H73: =$B$34 -> 0 | I73: =$B$34 -> 0 | J73: =$B$34 -> 0 | ... N73: =$B$34 -> 0
A74: Franchise Expenses | C74: =$B$30+$B$31+$B$32 -> 0 | D74: =$B$30+$B$31+$B$32 -> 0 | E74: =$B$30+$B$31+$B$32 -> 0 | F74: =$B$30+$B$31+$B$32 -> 0 | G74: =$B$30+$B$31+$B$32 -> 0 | H74: =$B$30+$B$31+$B$32 -> 0 | I74: =$B$30+$B$31+$B$32 -> 0 | J74: =$B$30+$B$31+$B$32 -> 0 | ... N74: =$B$30+$B$31+$B$32 -> 0
A75: Advertising/Marketing | C75: =$B$33 -> 0 | D75: =$B$33 -> 0 | E75: =$B$33 -> 0 | F75: =$B$33 -> 0 | G75: =$B$33 -> 0 | H75: =$B$33 -> 0 | I75: =$B$33 -> 0 | J75: =$B$33 -> 0 | ... N75: =$B$33 -> 0
A76: Rent/Property Expenses | C76: =($B$35+$B$36+$B$29)-(IF($B$46>0,$B$29,0)) -> 0 | D76: =($B$35+$B$36+$B$29)-(IF($B$46>1,$B$29,0)) -> 0 | E76: =($B$35+$B$36+$B$29)-(IF($B$46>2,$B$29,0)) -> 0 | F76: =($B$35+$B$36+$B$29)-(IF($B$46>3,$B$29,0)) -> 0 | G76: =($B$35+$B$36+$B$29)-(IF($B$46>4,$B$29,0)) -> 0 | H76: =($B$35+$B$36+$B$29)-(IF($B$46>5,$B$29,0)) -> 0 | I76: =($B$35+$B$36+$B$29)-(IF($B$46>6,$B$29,0)) -> 0 | J76: =($B$35+$B$36+$B$29)-(IF($B$46>7,$B$29,0)) -> 0 | K76: =($B$35+$B$36+$B$29)-(IF($B$46>8,$B$29,0)) -> 0 | L76: =($B$35+$B$36+$B$29)-(IF($B$46>9,$B$29,0)) -> 0 | M76: =($B$35+$B$36+$B$29)-(IF($B$46>10,$B$29,0)) -> 0 | N76: =($B$35+$B$36+$B$29)-(IF($B$46>11,$B$29,0)) -> 0
A77: Professional Expenses | C77: =$B$38+$B$37 -> 0 | D77: =$B$38+$B$37 -> 0 | E77: =$B$38+$B$37 -> 0 | F77: =$B$38+$B$37 -> 0 | G77: =$B$38+$B$37 -> 0 | H77: =$B$38+$B$37 -> 0 | I77: =$B$38+$B$37 -> 0 | J77: =$B$38+$B$37 -> 0 | ... N77: =$B$38+$B$37 -> 0
A78: Misc Expenses | C78: =$B$39+$B$40+$B$41+$B$42 -> 0 | D78: =$B$39+$B$40+$B$41+$B$42 -> 0 | E78: =$B$39+$B$40+$B$41+$B$42 -> 0 | F78: =$B$39+$B$40+$B$41+$B$42 -> 0 | G78: =$B$39+$B$40+$B$41+$B$42 -> 0 | H78: =$B$39+$B$40+$B$41+$B$42 -> 0 | I78: =$B$39+$B$40+$B$41+$B$42 -> 0 | J78: =$B$39+$B$40+$B$41+$B$42 -> 0 | ... N78: =$B$39+$B$40+$B$41+$B$42 -> 0
A79: Bad Debt | C79: =$B$43*C62 -> 0 | D79: =$B$43*D62 -> 0 | E79: =$B$43*E62 -> 0 | F79: =$B$43*F62 -> 0 | G79: =$B$43*G62 -> 0 | H79: =$B$43*H62 -> 0 | I79: =$B$43*I62 -> 0 | J79: =$B$43*J62 -> 0 | ... N79: =$B$43*N62 -> 0
A80: Operating Expenses | B80: =SUM(B73:B79) -> 0 | C80: =SUM(C73:C79) -> 0 | D80: =SUM(D73:D79) -> 0 | E80: =SUM(E73:E79) -> 0 | F80: =SUM(F73:F79) -> 0 | G80: =SUM(G73:G79) -> 0 | H80: =SUM(H73:H79) -> 0 | I80: =SUM(I73:I79) -> 0 | ... N80: =SUM(N73:N79) -> 0
A81: Total Expense | B81: =B71+B80 -> 0 | C81: =C71+C80 -> 0 | D81: =D71+D80 -> 0 | E81: =E71+E80 -> 0 | F81: =F71+F80 -> 0 | G81: =G71+G80 -> 0 | H81: =H71+H80 -> 0 | I81: =I71+I80 -> 0 | ... N81: =N71+N80 -> 0
A82: Net Income/(Loss) | B82: =B66-B81 -> 0 | C82: =C66-C81 -> 0 | D82: =D66-D81 -> 0 | E82: =E66-E81 -> 0 | F82: =F66-F81 -> 0 | G82: =G66-G81 -> 0 | H82: =H66-H81 -> 0 | I82: =I66-I81 -> 0 | ... N82: =N66-N81 -> 0
A83: Cumulative Results | B83: =B82 -> 0 | C83: =C82+B83 -> 0 | D83: =D82+C83 -> 0 | E83: =E82+D83 -> 0 | F83: =F82+E83 -> 0 | G83: =G82+F83 -> 0 | H83: =H82+G83 -> 0 | I83: =I82+H83 -> 0 | J83: =J82+I83 -> 0 | ... N83: =N82+M83 -> 0
A85: YEAR 2 | C85: Month 13 | D85: Month 14 | E85: Month 15 | F85: Month 16 | G85: Month 17 | H85: Month 18 | I85: Month 19 | J85: Month 20 | K85: Month 21 | L85: Month 22 | M85: Month 23 | N85: Month 24
A86: Monthly New Members
A87: (6) Single Members | C87: =ROUND((C86*(1-$B$6)),0) -> 0 | D87: =ROUND((D86*(1-$B$6)),0) -> 0 | E87: =ROUND((E86*(1-$B$6)),0) -> 0 | F87: =ROUND((F86*(1-$B$6)),0) -> 0 | G87: =ROUND((G86*(1-$B$6)),0) -> 0 | H87: =ROUND((H86*(1-$B$6)),0) -> 0 | I87: =ROUND((I86*(1-$B$6)),0) -> 0 | J87: =ROUND((J86*(1-$B$6)),0) -> 0 | ... N87: =ROUND((N86*(1-$B$6)),0) -> 0
A88: Member Attrition | C88: =-N55*($B$13/12) -> 0 | D88: =-C89*($B$13/12) -> 0 | E88: =-D89*($B$13/12) -> 0 | F88: =-E89*($B$13/12) -> 0 | G88: =-F89*($B$13/12) -> 0 | H88: =-G89*($B$13/12) -> 0 | I88: =-H89*($B$13/12) -> 0 | J88: =-I89*($B$13/12) -> 0 | K88: =-J89*($B$13/12) -> 0 | ... N88: =-M89*($B$13/12) -> 0
A89: Accumulated Single Members | C89: =N55+SUM(C87:C88) -> 0 | D89: =C89+SUM(D87:D88) -> 0 | E89: =D89+SUM(E87:E88) -> 0 | F89: =E89+SUM(F87:F88) -> 0 | G89: =F89+SUM(G87:G88) -> 0 | H89: =G89+SUM(H87:H88) -> 0 | I89: =H89+SUM(I87:I88) -> 0 | J89: =I89+SUM(J87:J88) -> 0 | K89: =J89+SUM(K87:K88) -> 0 | ... N89: =M89+SUM(N87:N88) -> 0
A90: Pay Per Visit "PPV" Members | C90: =ROUND(C86*$B$6,0) -> 0 | D90: =ROUND(D86*$B$6,0) -> 0 | E90: =ROUND(E86*$B$6,0) -> 0 | F90: =ROUND(F86*$B$6,0) -> 0 | G90: =ROUND(G86*$B$6,0) -> 0 | H90: =ROUND(H86*$B$6,0) -> 0 | I90: =ROUND(I86*$B$6,0) -> 0 | J90: =ROUND(J86*$B$6,0) -> 0 | ... N90: =ROUND(N86*$B$6,0) -> 0
A91: PPV Attrition | C91: =-N58*($B$13/12) -> 0 | D91: =-C92*($B$13/12) -> 0 | E91: =-D92*($B$13/12) -> 0 | F91: =-E92*($B$13/12) -> 0 | G91: =-F92*($B$13/12) -> 0 | H91: =-G92*($B$13/12) -> 0 | I91: =-H92*($B$13/12) -> 0 | J91: =-I92*($B$13/12) -> 0 | K91: =-J92*($B$13/12) -> 0 | ... N91: =-M92*($B$13/12) -> 0
A92: Accumulated PPV Members | C92: =+N58+SUM(C90:C91) -> 0 | D92: =+C92+SUM(D90:D91) -> 0 | E92: =+D92+SUM(E90:E91) -> 0 | F92: =+E92+SUM(F90:F91) -> 0 | G92: =+F92+SUM(G90:G91) -> 0 | H92: =+G92+SUM(H90:H91) -> 0 | I92: =+H92+SUM(I90:I91) -> 0 | J92: =+I92+SUM(J90:J91) -> 0 | K92: =+J92+SUM(K90:K91) -> 0 | ... N92: =+M92+SUM(N90:N91) -> 0
A93: Accumulating Total Members | C93: =C92+C89 -> 0 | D93: =D92+D89 -> 0 | E93: =E92+E89 -> 0 | F93: =F92+F89 -> 0 | G93: =G92+G89 -> 0 | H93: =H92+H89 -> 0 | I93: =I92+I89 -> 0 | J93: =J92+J89 -> 0 | ... N93: =N92+N89 -> 0
A94: Recur Single Memb Rev | C94: =C89*$B$10 -> 0 | D94: =D89*$B$10 -> 0 | E94: =E89*$B$10 -> 0 | F94: =F89*$B$10 -> 0 | G94: =G89*$B$10 -> 0 | H94: =H89*$B$10 -> 0 | I94: =I89*$B$10 -> 0 | J94: =J89*$B$10 -> 0 | ... N94: =N89*$B$10 -> 0
A95: Down Payment at Club | C95: =(C92*$B$11) -> 0 | D95: =(D92*$B$11) -> 0 | E95: =(E92*$B$11) -> 0 | F95: =(F92*$B$11) -> 0 | G95: =(G92*$B$11) -> 0 | H95: =(H92*$B$11) -> 0 | I95: =(I92*$B$11) -> 0 | J95: =(J92*$B$11) -> 0 | ... N95: =(N92*$B$11) -> 0
A96: Total Membership Rev | C96: =SUM(C94:C95) -> 0 | D96: =SUM(D94:D95) -> 0 | E96: =SUM(E94:E95) -> 0 | F96: =SUM(F94:F95) -> 0 | G96: =SUM(G94:G95) -> 0 | H96: =SUM(H94:H95) -> 0 | I96: =SUM(I94:I95) -> 0 | J96: =SUM(J94:J95) -> 0 | ... N96: =SUM(N94:N95) -> 0
A97: Vending/Misc Revenues | C97: =(+C93*$B$18)+(C93*$B$19)+(C93*$B$20) -> 0 | D97: =(+D93*$B$18)+(D93*$B$19)+(D93*$B$20) -> 0 | E97: =(+E93*$B$18)+(E93*$B$19)+(E93*$B$20) -> 0 | F97: =(+F93*$B$18)+(F93*$B$19)+(F93*$B$20) -> 0 | G97: =(+G93*$B$18)+(G93*$B$19)+(G93*$B$20) -> 0 | H97: =(+H93*$B$18)+(H93*$B$19)+(H93*$B$20) -> 0 | I97: =(+I93*$B$18)+(I93*$B$19)+(I93*$B$20) -> 0 | J97: =(+J93*$B$18)+(J93*$B$19)+(J93*$B$20) -> 0 | ... N97: =(+N93*$B$18)+(N93*$B$19)+(N93*$B$20) -> 0
A98: Personal Training Revenues | C98: =C93*$B$17 -> 0 | D98: =D93*$B$17 -> 0 | E98: =E93*$B$17 -> 0 | F98: =F93*$B$17 -> 0 | G98: =G93*$B$17 -> 0 | H98: =H93*$B$17 -> 0 | I98: =I93*$B$17 -> 0 | J98: =J93*$B$17 -> 0 | ... N98: =N93*$B$17 -> 0
A99: Enrollment Fees | C99: =C86*$B$9 -> 0 | D99: =D86*$B$9 -> 0 | E99: =E86*$B$9 -> 0 | F99: =F86*$B$9 -> 0 | G99: =G86*$B$9 -> 0 | H99: =H86*$B$9 -> 0 | I99: =I86*$B$9 -> 0 | J99: =J86*$B$9 -> 0 | ... N99: =N86*$B$9 -> 0
A100: Total Revenues | C100: =SUM(C96:C99) -> 0 | D100: =SUM(D96:D99) -> 0 | E100: =SUM(E96:E99) -> 0 | F100: =SUM(F96:F99) -> 0 | G100: =SUM(G96:G99) -> 0 | H100: =SUM(H96:H99) -> 0 | I100: =SUM(I96:I99) -> 0 | J100: =SUM(J96:J99) -> 0 | ... N100: =SUM(N96:N99) -> 0
A101: Payment processing | C101: =(C96*0.05)+((C99+C98)*0.015) -> 0 | D101: =(D96*0.05)+((D99+D98)*0.015) -> 0 | E101: =(E96*0.05)+((E99+E98)*0.015) -> 0 | F101: =(F96*0.05)+((F99+F98)*0.015) -> 0 | G101: =(G96*0.05)+((G99+G98)*0.015) -> 0 | H101: =(H96*0.05)+((H99+H98)*0.015) -> 0 | I101: =(I96*0.05)+((I99+I98)*0.015) -> 0 | J101: =(J96*0.05)+((J99+J98)*0.015) -> 0 | ... N101: =(N96*0.05)+((N99+N98)*0.015) -> 0
A102: Proximity Cards | C102: =C86*$B$25 -> 0 | D102: =D86*$B$25 -> 0 | E102: =E86*$B$25 -> 0 | F102: =F86*$B$25 -> 0 | G102: =G86*$B$25 -> 0 | H102: =H86*$B$25 -> 0 | I102: =I86*$B$25 -> 0 | J102: =J86*$B$25 -> 0 | ... N102: =N86*$B$25 -> 0
A103: Vending Costs | C103: =($B$18*C93)*$B$23 -> 0 | D103: =($B$18*D93)*$B$23 -> 0 | E103: =($B$18*E93)*$B$23 -> 0 | F103: =($B$18*F93)*$B$23 -> 0 | G103: =($B$18*G93)*$B$23 -> 0 | H103: =($B$18*H93)*$B$23 -> 0 | I103: =($B$18*I93)*$B$23 -> 0 | J103: =($B$18*J93)*$B$23 -> 0 | ... N103: =($B$18*N93)*$B$23 -> 0
A104: Personal Training Commissions | C104: =C98*$B$24 -> 0 | D104: =D98*$B$24 -> 0 | E104: =E98*$B$24 -> 0 | F104: =F98*$B$24 -> 0 | G104: =G98*$B$24 -> 0 | H104: =H98*$B$24 -> 0 | I104: =I98*$B$24 -> 0 | J104: =J98*$B$24 -> 0 | ... N104: =N98*$B$24 -> 0
A105: Total COGS | C105: =SUM(C101:C104) -> 0 | D105: =SUM(D101:D104) -> 0 | E105: =SUM(E101:E104) -> 0 | F105: =SUM(F101:F104) -> 0 | G105: =SUM(G101:G104) -> 0 | H105: =SUM(H101:H104) -> 0 | I105: =SUM(I101:I104) -> 0 | J105: =SUM(J101:J104) -> 0 | ... N105: =SUM(N101:N104) -> 0
A106: Gross Profit | C106: =C100-C105 -> 0 | D106: =D100-D105 -> 0 | E106: =E100-E105 -> 0 | F106: =F100-F105 -> 0 | G106: =G100-G105 -> 0 | H106: =H100-H105 -> 0 | I106: =I100-I105 -> 0 | J106: =J100-J105 -> 0 | ... N106: =N100-N105 -> 0
A107: Payroll & Employee Expenses | C107: =$B$34 -> 0 | D107: =$B$34 -> 0 | E107: =$B$34 -> 0 | F107: =$B$34 -> 0 | G107: =$B$34 -> 0 | H107: =$B$34 -> 0 | I107: =$B$34 -> 0 | J107: =$B$34 -> 0 | ... N107: =$B$34 -> 0
A108: Franchise Expenses | C108: =$B$30+$B$31+$B$32 -> 0 | D108: =$B$30+$B$31+$B$32 -> 0 | E108: =$B$30+$B$31+$B$32 -> 0 | F108: =$B$30+$B$31+$B$32 -> 0 | G108: =$B$30+$B$31+$B$32 -> 0 | H108: =$B$30+$B$31+$B$32 -> 0 | I108: =$B$30+$B$31+$B$32 -> 0 | J108: =$B$30+$B$31+$B$32 -> 0 | ... N108: =$B$30+$B$31+$B$32 -> 0
A109: Advertising/Marketing | C109: =$B$33 -> 0 | D109: =$B$33 -> 0 | E109: =$B$33 -> 0 | F109: =$B$33 -> 0 | G109: =$B$33 -> 0 | H109: =$B$33 -> 0 | I109: =$B$33 -> 0 | J109: =$B$33 -> 0 | ... N109: =$B$33 -> 0
A110: Rent/Property Expenses | C110: =($B$35+$B$36+$B$29)-(IF($B$46>12,$B$29,0)) -> 0 | D110: =($B$35+$B$36+$B$29)-(IF($B$46>13,$B$29,0)) -> 0 | E110: =($B$35+$B$36+$B$29)-(IF($B$46>14,$B$29,0)) -> 0 | F110: =($B$35+$B$36+$B$29)-(IF($B$46>15,$B$29,0)) -> 0 | G110: =($B$35+$B$36+$B$29)-(IF($B$46>16,$B$29,0)) -> 0 | H110: =($B$35+$B$36+$B$29)-(IF($B$46>17,$B$29,0)) -> 0 | I110: =($B$35+$B$36+$B$29)-(IF($B$46>18,$B$29,0)) -> 0 | J110: =($B$35+$B$36+$B$29)-(IF($B$46>19,$B$29,0)) -> 0 | K110: =($B$35+$B$36+$B$29)-(IF($B$46>20,$B$29,0)) -> 0 | L110: =($B$35+$B$36+$B$29)-(IF($B$46>21,$B$29,0)) -> 0 | M110: =($B$35+$B$36+$B$29)-(IF($B$46>22,$B$29,0)) -> 0 | N110: =($B$35+$B$36+$B$29)-(IF($B$46>23,$B$29,0)) -> 0
A111: Professional Expenses | C111: =$B$38+$B$37 -> 0 | D111: =$B$38+$B$37 -> 0 | E111: =$B$38+$B$37 -> 0 | F111: =$B$38+$B$37 -> 0 | G111: =$B$38+$B$37 -> 0 | H111: =$B$38+$B$37 -> 0 | I111: =$B$38+$B$37 -> 0 | J111: =$B$38+$B$37 -> 0 | ... N111: =$B$38+$B$37 -> 0
A112: Misc Expenses | C112: =$B$39+$B$40+$B$41+$B$42 -> 0 | D112: =$B$39+$B$40+$B$41+$B$42 -> 0 | E112: =$B$39+$B$40+$B$41+$B$42 -> 0 | F112: =$B$39+$B$40+$B$41+$B$42 -> 0 | G112: =$B$39+$B$40+$B$41+$B$42 -> 0 | H112: =$B$39+$B$40+$B$41+$B$42 -> 0 | I112: =$B$39+$B$40+$B$41+$B$42 -> 0 | J112: =$B$39+$B$40+$B$41+$B$42 -> 0 | ... N112: =$B$39+$B$40+$B$41+$B$42 -> 0
A113: Bad Debt | C113: =$B$43*C96 -> 0 | D113: =$B$43*D96 -> 0 | E113: =$B$43*E96 -> 0 | F113: =$B$43*F96 -> 0 | G113: =$B$43*G96 -> 0 | H113: =$B$43*H96 -> 0 | I113: =$B$43*I96 -> 0 | J113: =$B$43*J96 -> 0 | ... N113: =$B$43*N96 -> 0
A114: Operating Expenses | C114: =SUM(C107:C113) -> 0 | D114: =SUM(D107:D113) -> 0 | E114: =SUM(E107:E113) -> 0 | F114: =SUM(F107:F113) -> 0 | G114: =SUM(G107:G113) -> 0 | H114: =SUM(H107:H113) -> 0 | I114: =SUM(I107:I113) -> 0 | J114: =SUM(J107:J113) -> 0 | ... N114: =SUM(N107:N113) -> 0
A115: Total Expense | C115: =C105+C114 -> 0 | D115: =D105+D114 -> 0 | E115: =E105+E114 -> 0 | F115: =F105+F114 -> 0 | G115: =G105+G114 -> 0 | H115: =H105+H114 -> 0 | I115: =I105+I114 -> 0 | J115: =J105+J114 -> 0 | ... N115: =N105+N114 -> 0
A116: Net Income/(Loss) | C116: =C100-C115 -> 0 | D116: =D100-D115 -> 0 | E116: =E100-E115 -> 0 | F116: =F100-F115 -> 0 | G116: =G100-G115 -> 0 | H116: =H100-H115 -> 0 | I116: =I100-I115 -> 0 | J116: =J100-J115 -> 0 | ... N116: =N100-N115 -> 0
A117: Cumulative Results | C117: =C116+B117 -> 0 | D117: =D116+C117 -> 0 | E117: =E116+D117 -> 0 | F117: =F116+E117 -> 0 | G117: =G116+F117 -> 0 | H117: =H116+G117 -> 0 | I117: =I116+H117 -> 0 | J117: =J116+I117 -> 0 | ... N117: =N116+M117 -> 0
A119: YEAR 3 | C119: Month 25 | D119: Month 26 | E119: Month 27 | F119: Month 28 | G119: Month 29 | H119: Month 30 | I119: Month 31 | J119: Month 32 | K119: Month 33 | L119: Month 34 | M119: Month 35 | N119: Month 36
A120: Monthly New Members
A121: (6) Single Members | C121: =ROUND((C120*(1-$B$6)),0) -> 0 | D121: =ROUND((D120*(1-$B$6)),0) -> 0 | E121: =ROUND((E120*(1-$B$6)),0) -> 0 | F121: =ROUND((F120*(1-$B$6)),0) -> 0 | G121: =ROUND((G120*(1-$B$6)),0) -> 0 | H121: =ROUND((H120*(1-$B$6)),0) -> 0 | I121: =ROUND((I120*(1-$B$6)),0) -> 0 | J121: =ROUND((J120*(1-$B$6)),0) -> 0 | ... N121: =ROUND((N120*(1-$B$6)),0) -> 0
A122: Member Attrition | C122: =-N89*($B$13/12) -> 0 | D122: =-C123*($B$13/12) -> 0 | E122: =-D123*($B$13/12) -> 0 | F122: =-E123*($B$13/12) -> 0 | G122: =-F123*($B$13/12) -> 0 | H122: =-G123*($B$13/12) -> 0 | I122: =-H123*($B$13/12) -> 0 | J122: =-I123*($B$13/12) -> 0 | K122: =-J123*($B$13/12) -> 0 | ... N122: =-M123*($B$13/12) -> 0
...
