Workbook

Sheet Coaching Proforma
B1: AF Training Proforma | F1: *All sessions 60 minutes *4.3 weeks per month *2 visits per week average per client
B2: Insert data into double red cells.
B4: 15 | C4: 20 | D4: 30 | E4: 40 | F4: 60
B5: Functional Space Square Footage | D5: 0 | F5: =D5/75 -> 0
B7: Recommendations | C7: One-on-One Training | D7: Small Group Training | E7: Team Workouts | G7: Monthly Department P&L Summary | K7: Annual Department P&L Summary
B8: Capacity | C8: 1 | D8: 4 | E8: =IF(F5<8,"0",IF(F5>=8,F5)) -> 0 | G8: Revenue | H8: Payroll | I8: Client Count | K8: Revenue | L8: Payroll | M8: Gross Profit Margins
B9: Pricing | C9: 60 | D9: =IF(D5<=599, D4, IF(AND(D5>=600,D5<=899), E4, IF(D5>=900,D4))) -> 30 | E9: =IF(D5<=599, "0", IF(AND(D5>=600,D5<=899), C4, IF(D5>=900,B4))) -> 0 | G9: =SUM(L23:L27) -> 0 | H9: =SUM(M23:M27) -> 0 | I9: =F19+I19+L19 -> 0 | K9: =G9*12 -> 0 | L9: =H9*12 -> 0 | M9: =(K9-L9)/K9 -> #DIV/0!
C11: Weekly
A12: Weekly | C12: Shift | F12: One-on-One Training | I12: Small Group Training | L12: Team Workouts
C13: Hourly Wage | D13: Total Hours | E13: Base Compensation | F13: One-on-One Compensation | G13: One-on-One Serviced | H13: One-on-One Compensation | I13: SGT Session Compensation | J13: SGT Sessions Serviced | K13: SGT Compensation | L13: Team Session Compensation | M13: Team Sessions Serviced | N13: Team Compensation
B14: MXM | E14: =D14*C14 -> 0 | H14: =F14*G14 -> 0 | K14: =I14*J14 -> 0 | N14: =L14*M14 -> 0
B15: Coach 1 | E15: =D15*C15 -> 0 | H15: =F15*G15 -> 0 | K15: =I15*J15 -> 0 | N15: =L15*M15 -> 0
B16: Coach 2 | E16: =D16*C16 -> 0 | H16: =F16*G16 -> 0 | K16: =I16*J16 -> 0 | N16: =L16*M16 -> 0
B17: Coach 3 | E17: =D17*C17 -> 0 | H17: =F17*G17 -> 0 | K17: =I17*J17 -> 0 | N17: =L17*M17 -> 0
B18: Coach 4 | E18: =D18*C18 -> 0 | H18: =F18*G18 -> 0 | K18: =I18*J18 -> 0 | N18: =L18*M18 -> 0
F19: =(SUM(G14:G18))/2 -> 0 | G19: PT Clients | I19: =((SUM(J14:J18))*4)/2 -> 0 | J19: SGT Clients | L19: =((SUM(M14:M18))*E8)/2 -> 0 | M19: Team Clients
C20: Monthly
A21: Monthly | C21: Revenue Generated | F21: Bonus/Commisions Pay | I21: Total Compensation | L21: Staff P&L Summary
C22: One-on-One Training | D22: Small Group Training | E22: Team Workouts | F22: Individual Gross Percentage | G22: Department Gross Percentage | H22: Commission Compensation | I22: Average Hourly | J22: Total Monthly | K22: Total Annual | L22: Revenue | M22: Payroll | N22: Gross Profit Margins
B23: MXM | C23: =(G14*C9)*4.3 -> 0 | D23: =((J14*D9)*D8)*4.3 -> 0 | E23: =((M14*E9)*E8)*4.3 -> 0 | H23: =(F23*L23)+(G23*G9) -> 0 | I23: =J23/(D14*4.3) -> #DIV/0! | J23: =((E14+H14+K14+N14)*4.3)+H23 -> 0 | K23: =J23*12 -> 0 | L23: =C23+D23+E23 -> 0 | M23: =J23 -> 0 | N23: =(L23-M23)/L23 -> #DIV/0!
B24: Coach 1 | C24: =(G15*C9)*4.3 -> 0 | D24: =((J15*D9)*D8)*4.3 -> 0 | E24: =((M15*E9)*E8)*4.3 -> 0 | H24: =(F24*L24)+(G24*L24) -> 0 | I24: =J24/(D15*4.3) -> #DIV/0! | J24: =((E15+H15+K15+N15)*4.3)+H24 -> 0 | K24: =J24*12 -> 0 | L24: =C24+D24+E24 -> 0 | M24: =J24 -> 0 | N24: =(L24-M24)/L24 -> #DIV/0!
B25: Coach 2 | C25: =(G16*C9)*4.3 -> 0 | D25: =((J16*D9)*D8)*4.3 -> 0 | E25: =((M16*E9)*E8)*4.3 -> 0 | H25: =(F25*L25)+(G25*L25) -> 0 | I25: =J25/(D16*4.3) -> #DIV/0! | J25: =((E16+H16+K16+N16)*4.3)+H25 -> 0 | K25: =J25*12 -> 0 | L25: =C25+D25+E25 -> 0 | M25: =J25 -> 0 | N25: =(L25-M25)/L25 -> #DIV/0!
B26: Coach 3 | C26: =(G17*C9)*4.3 -> 0 | D26: =((J17*D9)*D8)*4.3 -> 0 | E26: =((M17*E9)*E8)*4.3 -> 0 | H26: =(F26*L26)+(G26*L26) -> 0 | I26: =J26/(D17*4.3) -> #DIV/0! | J26: =((E17+H17+K17+N17)*4.3)+H26 -> 0 | K26: =J26*12 -> 0 | L26: =C26+D26+E26 -> 0 | M26: =J26 -> 0 | N26: =(L26-M26)/L26 -> #DIV/0!
B27: Coach 4 | C27: =(G18*C9)*4.3 -> 0 | D27: =((J18*D9)*D8)*4.3 -> 0 | E27: =((M18*E9)*E8)*4.3 -> 0 | H27: =(F27*L27)+(G27*L27) -> 0 | I27: =J27/(D18*4.3) -> #DIV/0! | J27: =((E18+H18+K18+N18)*4.3)+H27 -> 0 | K27: =J27*12 -> 0 | L27: =C27+D27+E27 -> 0 | M27: =J27 -> 0 | N27: =(L27-M27)/L27 -> #DIV/0!
B30: “This proforma is being provided to you as a franchisee in the Anytime Fitness system. It is intended as a tool to assist you in evaluating your personal training programming, however we make no warranty regarding any particular results or accuracy of the information herein. Anytime Fitness, LLC does not provide or recommend revenue estimates or cost assumptions for your club, nor do we recommend particular compensation or other employment terms for your personnel. Once you make your own assumptions, the proforma populates the various columns using your assumptions. You may wish to consult with an accountant or other personal advisor to assist you in completing this proforma, and in analyzing any results produced.”

Sheet Coaching Projections
B1: AF Training Projections | F1: *Average monthly package in Club OS equals $152 *Average total agreement value in Club OS equals $1824 *Clients workout average of 2X per week
B2: Insert data into double red cells.
B4: KPI Goals
B5: Average Monthly New Members | C5: FCs @ POS % | D5: FC Show % | E5: FC Close % | F5: Avg PT Monthly Package Value | G5: Months to Goal | H5: Monthly add to Draft Goal
B6: 0 | C6: 0 | D6: 0 | E6: 0 | F6: 0 | G6: 0 | H6: ='Coaching Proforma'!G9/'Coaching Projections'!G6 -> #DIV/0!
D7: =D6*100 -> 0 | E7: =E6*100 -> 0
B8: Monthly Activity Goals
B9: Total New Packages Needed | C9: FCs @ POS Book | D9: FCs @ POS Show | E9: FCs @ POS Close | F9: Follow Up/TE Conversions Book | G9: Follow Up/TE Conversions Show | H9: Follow Up/TE Conversions Close
B10: =H6/F6 -> #DIV/0! | C10: =B6*C6 -> 0 | D10: =C10*D6 -> 0 | E10: =D10*E6 -> 0 | F10: =(100*G10)/D7 -> #DIV/0! | G10: =(E7*H10)/B10 -> #DIV/0! | H10: =B10-E10 -> #DIV/0!
B12: Weekly Activity Goals
B13: Total New Packages Needed | C13: FCs @ POS Book | D13: FCs @ POS Show | E13: FCs @ POS Close | F13: Follow Up/TE Conversions Book | G13: Follow Up/TE Conversions Show | H13: Follow Up/TE Conversions Close
B14: =B10/4.3 -> #DIV/0! | C14: =C10/4.3 -> 0 | D14: =D10/4.3 -> 0 | E14: =E10/4.3 -> 0 | F14: =F10/4.3 -> #DIV/0! | G14: =G10/4.3 -> #DIV/0! | H14: =H10/4.3 -> #DIV/0!
B16: 30 Day Training Experience to Launch Team Workouts
B17: Weekly Team Workouts | C17: Paid Trials Count Goal | D17: Paid Trial Cost | E17: Feeder Revenue | F17: New Client Count | G17: Projected Draft Added | H17: Total Agreement Value
B18: ='Coaching Proforma'!M14+'Coaching Proforma'!M15+'Coaching Proforma'!M16+'Coaching Proforma'!M17+'Coaching Proforma'!M18 -> 0 | C18: =(B18*'Coaching Proforma'!E8)/2 -> 0 | D18: 79 | E18: =C18*D18 -> 0 | F18: =C18*0.35 -> 0 | G18: =F18*152 -> 0 | H18: =G18*12 -> 0
B20: 30 Day Training Experience to Launch Small Group Training
B21: Weekly SGT Sessions | C21: Paid Trials Count Goal | D21: Paid Trial Cost | E21: Feeder Revenue | F21: New Client Count | G21: Projected Draft Added | H21: Total Agreement Value
B22: ='Coaching Proforma'!J14+'Coaching Proforma'!J15+'Coaching Proforma'!J16+'Coaching Proforma'!J17+'Coaching Proforma'!J18 -> 0 | C22: =(B22*'Coaching Proforma'!D8)/2 -> 0 | D22: 179 | E22: =C22*D22 -> 0 | F22: =C22*0.35 -> 0 | G22: =F22*152 -> 0 | H22: =G22*12 -> 0
B24: “This proforma is being provided to you as a franchisee in the Anytime Fitness system. It is intended as a tool to assist you in evaluating your personal training programming, however we make no warranty regarding any particular results or accuracy of the information herein. Anytime Fitness, LLC does not provide or recommend revenue estimates or cost assumptions for your club, nor do we recommend particular compensation or other employment terms for your personnel. Once you make your own assumptions, the proforma populates the various columns using your assumptions. You may wish to consult with an accountant or other personal advisor to assist you in completing this proforma, and in analyzing any results produced.”
